comparemol/__init__.py
comparemol/config.py
comparemol/mol.py
comparemol/rotate.py
comparemol-0.0.2.dist-info/LICENSE
comparemol-0.0.2.dist-info/METADATA
comparemol-0.0.2.dist-info/WHEEL
comparemol-0.0.2.dist-info/top_level.txt
comparemol-0.0.2.dist-info/RECORD
