Metadata-Version: 2.1
Name: comparemol
Version: 0.0.2
Summary: Compare if two molecules are equivalent.
Author-email: Jinzhe Zeng <jinzhe.zeng@rutgers.edu>
License: GNU LESSER GENERAL PUBLIC LICENSE
Project-URL: Homepage, https://github.com/njzjz/comparemol
Project-URL: repository, https://github.com/njzjz/comparemol
Keywords: compare,molecule,equivalent
Classifier: Programming Language :: Python :: 3.8
Classifier: Programming Language :: Python :: 3.9
Classifier: Programming Language :: Python :: 3.10
Classifier: Programming Language :: Python :: 3.11
Classifier: Operating System :: POSIX :: Linux
Classifier: Operating System :: MacOS :: MacOS X
Classifier: Operating System :: Microsoft :: Windows
Classifier: License :: OSI Approved :: GNU Lesser General Public License v3 (LGPLv3)
Requires-Python: >=3.8
License-File: LICENSE
Requires-Dist: numpy
Requires-Dist: scipy
Provides-Extra: test
Requires-Dist: pytest ; extra == 'test'
Requires-Dist: dpdata ; extra == 'test'
